{
  "model_name": "traffic_forecasting_lightgbm",
  "model_type": "LightGBMRegressor",
  "trained_at": "2026-06-17T19:23:50.737855+00:00",
  "dataset_path": "data/gold/train_features_15m.parquet",
  "target_column": "target_speed",
  "feature_columns": [
    "city",
    "segment_id",
    "currentSpeed",
    "freeFlowSpeed",
    "jamFactor",
    "confidence",
    "lat",
    "lon",
    "date",
    "hour_of_day",
    "day_of_week",
    "day_of_month",
    "is_weekend",
    "is_peak_hour",
    "congestion_ratio",
    "speed_lag_1",
    "congestion_lag_1",
    "speed_lag_2",
    "congestion_lag_2",
    "speed_lag_3",
    "congestion_lag_3",
    "speed_lag_4",
    "congestion_lag_4",
    "speed_lag_5",
    "congestion_lag_5",
    "speed_lag_6",
    "congestion_lag_6",
    "speed_lag_7",
    "congestion_lag_7",
    "speed_lag_8",
    "congestion_lag_8",
    "speed_lag_9",
    "congestion_lag_9",
    "speed_lag_10",
    "congestion_lag_10",
    "speed_lag_11",
    "congestion_lag_11",
    "speed_lag_12",
    "congestion_lag_12",
    "speed_trend_1",
    "speed_trend_2",
    "speed_acceleration",
    "speed_rolling_avg_15m",
    "speed_rolling_avg_30m",
    "speed_rolling_avg_60m",
    "congestion_rolling_avg_15m",
    "congestion_rolling_avg_30m",
    "congestion_rolling_avg_60m",
    "speed_volatility_15m",
    "speed_volatility_30m",
    "valid_history_30m",
    "valid_history_60m",
    "weather_temperature",
    "weather_humidity",
    "weather_rain_1h",
    "weather_wind_speed",
    "has_rain",
    "weather_severity",
    "has_accident",
    "has_any_event",
    "news_event_count_1h",
    "news_event_count_3h",
    "news_event_count_6h",
    "accident_count_1h",
    "max_event_severity_1h",
    "max_event_severity_6h",
    "avg_traffic_relevance_score_6h",
    "has_recent_accident"
  ],
  "metrics": {
    "mae": 1.3013261451658396,
    "rmse": 1.7207364775462795,
    "mape": 5.525406084764983,
    "r2": 0.47212451269608924
  },
  "artifact_path": "models/artifacts/traffic_model.joblib",
  "limitations": [
    "Model validity depends on the quality and realism of the training dataset.",
    "If trained on synthetic/calibrated data, real-world predictive performance is not guaranteed."
  ]
}